pyzohar/__init__.py
pyzohar/samples/logo_centaline.png
pyzohar/samples/smp01.xlsx
pyzohar/sub_slt_bsc/__init__.py
pyzohar/sub_slt_bsc/bsz.py
pyzohar/sub_slt_bsc/dfz.py
pyzohar/sub_slt_bsc/ioz.py
pyzohar/sub_slt_mdl/__init__.py
pyzohar/sub_slt_mdl/mdz.py
pyzohar/sub_slt_ppt/__init__.py
pyzohar/sub_slt_ppt/ppz.py
pyzohar/sub_slt_spd/__init__.py
pyzohar/sub_slt_spd/spz.py
pyzohar-0.1.19.dist-info/LICENCE
pyzohar-0.1.19.dist-info/METADATA
pyzohar-0.1.19.dist-info/WHEEL
pyzohar-0.1.19.dist-info/top_level.txt
pyzohar-0.1.19.dist-info/RECORD
