Metadata-Version: 2.1
Name: pyzohar
Version: 0.1.19
Summary: a private package on data pre-processing.
Home-page: https://zoharslong.com/#/pyzohar
Author: zoharslong
Author-email: zoharslong@hotmail.com
License: MIT
Keywords: data pre-processing
Classifier: Development Status :: 3 - Alpha
Classifier: Intended Audience :: Developers
Classifier: Topic :: Software Development :: Build Tools
Classifier: License :: OSI Approved :: MIT License
Classifier: Programming Language :: Python :: 3
Classifier: Programming Language :: Python :: 3.6
Classifier: Programming Language :: Python :: 3.7
Classifier: Programming Language :: Python :: 3.8
Classifier: Programming Language :: Python :: 3.9
Requires-Python: >=3
License-File: LICENCE
Requires-Dist: numpy>=1.18.1
Requires-Dist: pandas>=1.0.1
Requires-Dist: pymongo>=3.9.0
Requires-Dist: pymysql>=0.9.3
Requires-Dist: fake-useragent>=0.1.11
Requires-Dist: requests>=2.22.0
Requires-Dist: openpyxl>=3.0.3
Requires-Dist: urllib3>=1.25.8
